MANIFEST.in
README.rst
setup.py
docs/HISTORY.txt
docs/LICENSE.GPL
docs/LICENSE.txt
ftw/__init__.py
ftw.tika.egg-info/PKG-INFO
ftw.tika.egg-info/SOURCES.txt
ftw.tika.egg-info/dependency_links.txt
ftw.tika.egg-info/entry_points.txt
ftw.tika.egg-info/namespace_packages.txt
ftw.tika.egg-info/not-zip-safe
ftw.tika.egg-info/requires.txt
ftw.tika.egg-info/top_level.txt
ftw/tika/__init__.py
ftw/tika/configure.zcml
ftw/tika/converter.py
ftw/tika/exceptions.py
ftw/tika/interfaces.py
ftw/tika/meta.zcml
ftw/tika/profiles.zcml
ftw/tika/protected_docs.py
ftw/tika/setuphandlers.py
ftw/tika/testing.py
ftw/tika/utils.py
ftw/tika/zcml.py
ftw/tika/mimetypes/__init__.py
ftw/tika/profiles/default/ftw.tika.default.txt
ftw/tika/profiles/default/metadata.xml
ftw/tika/profiles/uninstall/ftw.tika.uninstall.txt
ftw/tika/tests/__init__.py
ftw/tika/tests/helpers.py
ftw/tika/tests/test_converter.py
ftw/tika/tests/test_converter_local.py
ftw/tika/tests/test_converter_server.py
ftw/tika/tests/test_installation.py
ftw/tika/tests/test_integration.py
ftw/tika/tests/test_meta_directive.py
ftw/tika/tests/test_transforms.py
ftw/tika/tests/test_utils.py
ftw/tika/tests/test_zcml_directive.py
ftw/tika/tests/utils.py
ftw/tika/tests/assets/lorem.doc
ftw/tika/tests/assets/lorem.docx
ftw/tika/tests/assets/lorem.eml
ftw/tika/tests/assets/lorem.odt
ftw/tika/tests/assets/lorem.pdf
ftw/tika/tests/assets/lorem.ppt
ftw/tika/tests/assets/lorem.pptx
ftw/tika/tests/assets/lorem.rtf
ftw/tika/tests/assets/lorem.sxw
ftw/tika/tests/assets/lorem.xls
ftw/tika/tests/assets/lorem.xlsx
ftw/tika/tests/assets/protected.docx
ftw/tika/tests/assets/protected.pdf
ftw/tika/tests/assets/protected.txt
ftw/tika/transforms/__init__.py
ftw/tika/transforms/tika_to_plain_text.py