Metadata-Version: 1.1
Name: ftw.tika
Version: 2.9.0
Summary: Apache Tika integration for Plone using portal transforms.
Home-page: https://github.com/4teamwork/ftw.tika
Author: 4teamwork AG
Author-email: mailto:info@4teamwork.ch
License: GPL2
Keywords: plone ftw tika full text indexing apache
Platform: UNKNOWN
Classifier: Framework :: Plone
Classifier: Framework :: Plone :: 4.2
Classifier: Framework :: Plone :: 4.3
Classifier: Intended Audience :: Developers
Classifier: License :: OSI Approved :: GNU General Public License (GPL)
Classifier: Programming Language :: Python
Classifier: Topic :: Software Development
